{
    "values": [
        "minecraft:bread",
        "minecraft:cookie",
        "minecraft:cake",
        {
            "id": "farmersdelight:wheat_dough",
            "required": false
        },
        {
            "id": "farmersdelight:raw_pasta",
            "required": false
        },
        {
            "id": "farmersdelight:pie_crust",
            "required": false
        },
        {
            "id": "farmersdelight:sweet_berry_cookie",
            "required": false
        },
        {
            "id": "farmersdelight:honey_cookie",
            "required": false
        },
        {
            "id": "farmersdelight:cooked_rice",
            "required": false
        },
        {
            "id": "farmersdelight:fried_rice",
            "required": false
        },
        {
            "id": "farmersdelight:chocolate_pie",
            "required": false
        },
        {
            "id": "farmersdelight:chocolate_pie_slice",
            "required": false
        },
        {
            "id": "nears:cinder_sangak",
            "required": false
        },
        {
            "id": "rusticdelight:batter",
            "required": false
        },
        {
            "id": "rusticdelight:syrup_cheesecake",
            "required": false
        },
        {
            "id": "rusticdelight:syrup_cheesecake_slice",
            "required": false
        },
        {
            "id": "rusticdelight:cherry_blossom_cheesecake",
            "required": false
        },
        {
            "id": "rusticdelight:cherry_blossom_cheesecake_slice",
            "required": false
        },
        {
            "id": "rusticdelight:syrup_cookie",
            "required": false
        },
        {
            "id": "rusticdelight:cherry_blossom_cookie",
            "required": false
        },
        {
            "id": "rusticdelight:syrup_cheesecake",
            "required": false
        },
        {
            "id": "rusticdelight:coffee_cookie",
            "required": false
        },
        {
            "id": "rusticdelight:syrup_sandwich",
            "required": false
        },
        {
            "id": "rusticdelight:fruit_beignet",
            "required": false
        },
        {
            "id": "rusticdelight:pancakes",
            "required": false
        },
        {
            "id": "rusticdelight:pancake",
            "required": false
        },
        {
            "id": "rusticdelight:honey_pancakes",
            "required": false
        },
        {
            "id": "rusticdelight:honey_pancake",
            "required": false
        },
        {
            "id": "rusticdelight:chocolate_pancakes",
            "required": false
        },
        {
            "id": "rusticdelight:chocolate_pancake",
            "required": false
        },
        {
            "id": "rusticdelight:cherry_blossom_pancakes",
            "required": false
        },
        {
            "id": "rusticdelight:cherry_blossom_pancake",
            "required": false
        },
        {
            "id": "rusticdelight:vegetable_pancakes",
            "required": false
        },
        {
            "id": "rusticdelight:vegetable_pancake",
            "required": false
        },
        {
            "id": "rusticdelight:pumpkin_pancakes",
            "required": false
        },
        {
            "id": "rusticdelight:pumpkin_pancake",
            "required": false
        },
        {
            "id": "rusticdelight:fried_dough",
            "required": false
        }
    ]
}
